microlensing/CCF/__init__.py
microlensing/CCF/ccf.py
microlensing/CCF/lib_ccf.py
microlensing/IPM/__init__.py
microlensing/IPM/ipm.py
microlensing/IPM/lib_ipm.py
microlensing/IPM/lib_ipm_double.py
microlensing/Lightcurves/__init__.py
microlensing/Lightcurves/lightcurves.py
microlensing/Lightcurves/ncc_curves.py
microlensing/Lightcurves/util.py
microlensing/MIF/__init__.py
microlensing/MIF/lib_mif.py
microlensing/MIF/mif.py
microlensing/MIF/plotting.py
microlensing/NCC/__init__.py
microlensing/NCC/distances.py
microlensing/NCC/lib_ncc.py
microlensing/NCC/ncc.py
microlensing/SourceProfiles/__init__.py
microlensing/SourceProfiles/gaussian.py
microlensing/SourceProfiles/uniform_disk.py
microlensing/Stars/__init__.py
microlensing/Stars/plotting.py
microlensing/Stars/stars.py
microlensing/Supernovae/__init__.py
microlensing/Supernovae/chromatic_microlensing.py
microlensing/Util/__init__.py
microlensing/Util/length_scales.py
microlensing/Util/util.py
microlensing/lib/lib_ccf.so
microlensing/lib/lib_ipm.so
microlensing/lib/lib_ipm_double.so
microlensing/lib/lib_mif.so
microlensing/lib/lib_ncc.so
microlensing-0.1.7.dist-info/licenses/LICENSE.txt
microlensing-0.1.7.dist-info/METADATA
microlensing-0.1.7.dist-info/WHEEL
microlensing-0.1.7.dist-info/top_level.txt
microlensing-0.1.7.dist-info/RECORD
