Metadata-Version: 2.4
Name: microlensing
Version: 0.1.7
Summary: A package for microlensing simulations
Home-page: https://github.com/weisluke/microlensing/
Author: Luke Weisenbach
Author-email: weisluke@alum.mit.edu
License: GNU AFFERO GENERAL PUBLIC LICENSE
Platform: linux_x86_64
Requires-Python: >=3.10
License-File: LICENSE.txt
Requires-Dist: numpy
Requires-Dist: scipy
Requires-Dist: astropy
Requires-Dist: matplotlib
Requires-Dist: sncosmo>=2.10
Dynamic: author
Dynamic: author-email
Dynamic: description
Dynamic: description-content-type
Dynamic: home-page
Dynamic: license
Dynamic: license-file
Dynamic: platform
Dynamic: requires-dist
Dynamic: requires-python
Dynamic: summary
